{
  "project_info": {
    "project_number": "511369160204",
    "project_id": "webbcheck",
    "storage_bucket": "webbcheck.appspot.com"
  },
  "client": [
    {
      "client_info": {
        "mobilesdk_app_id": "1:511369160204:android:bd59fb4b7d64934ea73029",
        "android_client_info": {
          "package_name": "com.webbpulse.checkout"
        }
      },
      "oauth_client": [],
      "api_key": [
        {
          "current_key": "AIzaSyDV8sHYVYw2LIVqyov8d9HGCL7Qw_7FtT8"
        }
      ],
      "services": {
        "appinvite_service": {
          "other_platform_oauth_client": []
        }
      }
    }
  ],
  "configuration_version": "1"
}